LICENSE
MANIFEST.in
README.md
requirements.txt
setup.cfg
setup.py
accounts/__init__.py
accounts/forms.py
accounts/tokens.py
accounts/urls.py
accounts/views.py
accounts/locale/en/LC_MESSAGES/django.mo
accounts/locale/en/LC_MESSAGES/django.po
accounts/locale/ru/LC_MESSAGES/django.mo
accounts/locale/ru/LC_MESSAGES/django.po
accounts/locale/uk/LC_MESSAGES/django.mo
accounts/locale/uk/LC_MESSAGES/django.po
accounts/templates/accounts/base-email.html
accounts/templates/accounts/base-profile.html
accounts/templates/accounts/login.html
accounts/templates/accounts/password-change.html
accounts/templates/accounts/password-reset-confirm.html
accounts/templates/accounts/password-reset-email.html
accounts/templates/accounts/password-reset-subject.txt
accounts/templates/accounts/password-reset.html
accounts/templates/accounts/profile-change.html
accounts/templates/accounts/profile-remove.html
accounts/templates/accounts/profile.html
accounts/templates/accounts/signup-email.html
accounts/templates/accounts/signup-subject.txt
accounts/templates/accounts/signup.html
django_mp_accounts.egg-info/PKG-INFO
django_mp_accounts.egg-info/SOURCES.txt
django_mp_accounts.egg-info/dependency_links.txt
django_mp_accounts.egg-info/requires.txt
django_mp_accounts.egg-info/top_level.txt