Metadata-Version: 1.1
Name: django-mp-accounts
Version: 3.2
Summary: Django accounts app
Home-page: https://github.com/pmaigutyak/mp-accounts
Author: Paul Maigutyak
Author-email: pmaigutyak@gmail.com
License: MIT
Download-URL: https://github.com/pmaigutyak/mp-accounts/archive/3.2.tar.gz
Platform: UNKNOWN
